LICENSE.txt
edgar/__about__.py
edgar/__init__.py
edgar/_filings.py
edgar/_markdown.py
edgar/_party.py
edgar/async_api.py
edgar/attachments.py
edgar/company_reports.py
edgar/core.py
edgar/current_filings.py
edgar/datatools.py
edgar/dates.py
edgar/effect.py
edgar/enums.py
edgar/filtering.py
edgar/financials.py
edgar/form144.py
edgar/formatting.py
edgar/forms.py
edgar/headers.py
edgar/httpclient.py
edgar/httprequests.py
edgar/muniadvisors.py
edgar/richtools.py
edgar/shelfofferings.py
edgar/storage.py
edgar/thirteenf.py
edgar/xmltools.py
edgar/ai/__init__.py
edgar/ai/core.py
edgar/ai/edgartools_mcp_server.py
edgar/ai/minimal_mcp_server.py
edgar/ai/run_mcp_server.py
edgar/ai/docs/ai-function-patterns.md
edgar/ai/docs/ai-mcp-package-structure-plan.md
edgar/ai/docs/edgartools-mcp-ai-support.md
edgar/ai/edgartools_mcp/__init__.py
edgar/ai/edgartools_mcp/server.py
edgar/ai/edgartools_mcp/simple_server.py
edgar/ai/edgartools_mcp/tools.py
edgar/ai/examples/__init__.py
edgar/ai/examples/basic_usage.py
edgar/docs/Filing.md
edgar/docs/Filings.md
edgar/documents/__init__.py
edgar/documents/config.py
edgar/documents/document.py
edgar/documents/exceptions.py
edgar/documents/migration.py
edgar/documents/migration_example.py
edgar/documents/nodes.py
edgar/documents/parser.py
edgar/documents/search.py
edgar/documents/simple_parser.py
edgar/documents/table_nodes.py
edgar/documents/types.py
edgar/documents/extractors/__init__.py
edgar/documents/extractors/section_extractor.py
edgar/documents/extractors/text_extractor.py
edgar/documents/processors/__init__.py
edgar/documents/processors/postprocessor.py
edgar/documents/processors/preprocessor.py
edgar/documents/renderers/__init__.py
edgar/documents/renderers/markdown.py
edgar/documents/renderers/text.py
edgar/documents/strategies/__init__.py
edgar/documents/strategies/document_builder.py
edgar/documents/strategies/header_detection.py
edgar/documents/strategies/style_parser.py
edgar/documents/strategies/table_processing.py
edgartools_async-1.0.16.dist-info/METADATA
edgartools_async-1.0.16.dist-info/WHEEL
edgartools_async-1.0.16.dist-info/licenses/LICENSE.txt
edgartools_async-1.0.16.dist-info/RECORD
