Metadata-Version: 2.4
Name: edgartools-async
Version: 1.0.16
Summary: Async-enabled fork of edgartools with enhanced XBRL support for non-US GAAP financial statements
Project-URL: Documentation, https://dgunning.github.io/edgartools/
Project-URL: Issues, https://github.com/lucasastorian/edgartools/issues
Project-URL: Source, https://github.com/lucasastorian/edgartools
Project-URL: Original Source, https://github.com/dgunning/edgartools
Author-email: Dwight Gunning <dgunning@gmail.com>, Lucas Astorian <lucas@intellifin.ai>
Maintainer-email: Lucas Astorian <lucas@intellifin.ai>
License-Expression: MIT
License-File: LICENSE.txt
Keywords: async,asyncio,company,edgar,filings,finance,financial,ifrs,non-us-gaap,python,reports,sec,xbrl
Classifier: Development Status :: 4 - Beta
Classifier: License :: OSI Approved :: MIT License
Classifier: Programming Language :: Python
Classifier: Programming Language :: Python :: 3.10
Classifier: Programming Language :: Python :: 3.11
Classifier: Programming Language :: Python :: 3.12
Classifier: Programming Language :: Python :: 3.13
Classifier: Programming Language :: Python :: Implementation :: CPython
Classifier: Programming Language :: Python :: Implementation :: PyPy
Requires-Python: >=3.10
Requires-Dist: beautifulsoup4>=4.10.0
Requires-Dist: hishel<1.0.0,>=0.1.3
Requires-Dist: httpx>=0.25.0
Requires-Dist: httpxthrottlecache>=0.1.6
Requires-Dist: humanize>=4.0.0
Requires-Dist: jinja2>=3.1.0
Requires-Dist: lxml>=4.4
Requires-Dist: nest-asyncio>=1.5.1
Requires-Dist: orjson>=3.6.0
Requires-Dist: pandas>=2.0.0
Requires-Dist: pyarrow>=17.0.0
Requires-Dist: pydantic>=2.0.0
Requires-Dist: rank-bm25>=0.2.1
Requires-Dist: rapidfuzz>=3.5.0
Requires-Dist: rich>=13.8.0
Requires-Dist: stamina>=24.2.0
Requires-Dist: tabulate>=0.9.0
Requires-Dist: textdistance>=4.5.0
Requires-Dist: tqdm>=4.62.0
Requires-Dist: unidecode>=1.2.0
Provides-Extra: ai
Requires-Dist: mcp==1.12.3; (python_version >= '3.10') and extra == 'ai'
Requires-Dist: tiktoken>=0.10.0; extra == 'ai'
Provides-Extra: ai-dev
Requires-Dist: pytest-mock>=3.12.0; extra == 'ai-dev'
Requires-Dist: responses>=0.24.0; extra == 'ai-dev'
